deadline/max_adaptor/__init__.py
deadline/max_adaptor/_version.py
deadline/max_adaptor/executable_handler.py
deadline/max_adaptor/MaxAdaptor/MaxAdaptor.json
deadline/max_adaptor/MaxAdaptor/__init__.py
deadline/max_adaptor/MaxAdaptor/__main__.py
deadline/max_adaptor/MaxAdaptor/adaptor.py
deadline/max_adaptor/MaxAdaptor/py.typed
deadline/max_adaptor/MaxAdaptor/regex_callback_handler.py
deadline/max_adaptor/MaxAdaptor/schemas/init_data.schema.json
deadline/max_adaptor/MaxAdaptor/schemas/run_data.schema.json
deadline/max_adaptor/MaxClient/__init__.py
deadline/max_adaptor/MaxClient/logger_interceptor.py
deadline/max_adaptor/MaxClient/max_client.py
deadline/max_adaptor/MaxClient/py.typed
deadline/max_adaptor/MaxClient/render_element_manager.py
deadline/max_adaptor/MaxClient/render_handlers/__init__.py
deadline/max_adaptor/MaxClient/render_handlers/art_handler.py
deadline/max_adaptor/MaxClient/render_handlers/corona_handler.py
deadline/max_adaptor/MaxClient/render_handlers/default_max_handler.py
deadline/max_adaptor/MaxClient/render_handlers/redshift_handler.py
deadline/max_adaptor/MaxClient/render_handlers/vray_handler.py
deadline/max_shared/README.md
deadline/max_shared/__init__.py
deadline/max_shared/utilities/__init__.py
deadline/max_shared/utilities/max_utils.py
deadline/max_submitter/__init__.py
deadline/max_submitter/_version.py
deadline/max_submitter/adaptor_override_environment.yaml
deadline/max_submitter/create_job_bundle.py
deadline/max_submitter/data_classes.py
deadline/max_submitter/data_const.py
deadline/max_submitter/default_max_job_template.yaml
deadline/max_submitter/job_bundle_output_test_runner.py
deadline/max_submitter/max_render_submitter.py
deadline/max_submitter/run_ui.py
deadline/max_submitter/sanity_checks.py
deadline/max_submitter/ui/__init__.py
deadline/max_submitter/ui/render_elements_widget.py
deadline/max_submitter/ui/scene_settings_tab.py
deadline/max_submitter/ui/submit_dialog.py
deadline/max_submitter/utilities/__init__.py
deadline_cloud_for_3ds_max-0.1.7.dist-info/METADATA
deadline_cloud_for_3ds_max-0.1.7.dist-info/WHEEL
deadline_cloud_for_3ds_max-0.1.7.dist-info/entry_points.txt
deadline_cloud_for_3ds_max-0.1.7.dist-info/licenses/LICENSE
deadline_cloud_for_3ds_max-0.1.7.dist-info/licenses/NOTICE
deadline_cloud_for_3ds_max-0.1.7.dist-info/RECORD
